cmdcomp/__init__.py
cmdcomp/__main__.py
cmdcomp/app.py
cmdcomp/completion.py
cmdcomp/config.py
cmdcomp/exception.py
cmdcomp/model.py
cmdcomp/shell.py
cmdcomp/v1/__init__.py
cmdcomp/v1/app_info.py
cmdcomp/v1/cmdcomp_info.py
cmdcomp/v1/command/__init__.py
cmdcomp/v1/command/option/__init__.py
cmdcomp/v1/command/option/command_option.py
cmdcomp/v1/command/option/file_option.py
cmdcomp/v1/completion.py
cmdcomp/v1/config.py
cmdcomp/v1/templates/bash.sh.jinja
cmdcomp/v1/templates/zsh.sh.jinja
cmdcomp/v2/__init__.py
cmdcomp/v2/app_info.py
cmdcomp/v2/cmdcomp_info.py
cmdcomp/v2/command/__init__.py
cmdcomp/v2/command/argument/__init__.py
cmdcomp/v2/command/argument/command_argument.py
cmdcomp/v2/command/argument/file_argument.py
cmdcomp/v2/command/argument/flag_argument.py
cmdcomp/v2/command/argument/select_argument.py
cmdcomp/v2/command/base_command.py
cmdcomp/v2/command/delegate_command.py
cmdcomp/v2/command/empty_command.py
cmdcomp/v2/command/positional_arguments_command.py
cmdcomp/v2/command/subcommands_command.py
cmdcomp/v2/completion.py
cmdcomp/v2/config.py
cmdcomp/v2/mixin/has_alias.py
cmdcomp/v2/templates/bash.sh.jinja
cmdcomp/v2/templates/zsh.sh.jinja
cmdcomp-2.6.0.dist-info/METADATA
cmdcomp-2.6.0.dist-info/WHEEL
cmdcomp-2.6.0.dist-info/entry_points.txt
cmdcomp-2.6.0.dist-info/RECORD
