Metadata-Version: 2.1
Name: cmdcomp
Version: 2.6.0
Summary: command shell completion file generator.
Home-page: https://yassun7010.github.io/cmdcomp/
License: BSD-3-Clause
Author: yassun7010
Author-email: yassun7010@outlook.com
Requires-Python: >=3.11,<4.0
Classifier: Development Status :: 5 - Production/Stable
Classifier: Intended Audience :: Developers
Classifier: License :: OSI Approved :: BSD License
Classifier: Programming Language :: Python :: 3
Classifier: Programming Language :: Python :: 3.11
Classifier: Programming Language :: Python :: 3.12
Classifier: Programming Language :: Python :: 3 :: Only
Classifier: Topic :: Software Development
Classifier: Typing :: Typed
Requires-Dist: jinja2 (>=3.1.2,<4.0.0)
Requires-Dist: mergedeep (>=1.3.4,<2.0.0)
Requires-Dist: pydantic (>=2.3,<3.0)
Requires-Dist: pyyaml (>=6.0,<7.0)
Requires-Dist: rich (>=13.4.2,<14.0.0)
Requires-Dist: rich-argparse (>=1.3.0,<2.0.0)
Requires-Dist: typing-extensions (>=4.7.1,<5.0.0)
Project-URL: Repository, https://github.com/yassun7010/cmdcomp
